sloplog/__init__.py
sloplog/core.py
sloplog/partials.py
sloplog/py.typed
sloplog/collectors/__init__.py
sloplog/collectors/base.py
sloplog/collectors/betterstack.py
sloplog/collectors/file.py
sloplog/collectors/sentry.py
sloplog/collectors/stdio.py
sloplog/originator/__init__.py
sloplog-0.0.13.dist-info/METADATA
sloplog-0.0.13.dist-info/WHEEL
sloplog-0.0.13.dist-info/RECORD
