Metadata-Version: 2.4
Name: sloplog
Version: 0.0.13
Summary: A Python library for constructing wide events
Project-URL: Homepage, https://github.com/cmsparks/sloplog
Project-URL: Repository, https://github.com/cmsparks/sloplog
Project-URL: Documentation, https://github.com/cmsparks/sloplog#readme
Project-URL: Issues, https://github.com/cmsparks/sloplog/issues
Author-email: Your Name <your.email@example.com>
License-Expression: MIT
Keywords: logging,observability,structured-logging,tracing,wide-events
Classifier: Development Status :: 4 - Beta
Classifier: Intended Audience :: Developers
Classifier: License :: OSI Approved :: MIT License
Classifier: Programming Language :: Python :: 3
Classifier: Programming Language :: Python :: 3.12
Classifier: Programming Language :: Python :: 3.13
Classifier: Topic :: Software Development :: Libraries :: Python Modules
Classifier: Topic :: System :: Logging
Classifier: Typing :: Typed
Requires-Python: >=3.12
Requires-Dist: aiofiles
Provides-Extra: test
Requires-Dist: pytest; extra == 'test'
Requires-Dist: pytest-asyncio; extra == 'test'
